casbin_async_redis_adapter/__init__.py
casbin_async_redis_adapter/adapter.py
tests/__init__.py
tests/test_adapter.py
casbin_async_redis_adapter-1.2.0.dist-info/LICENSE
casbin_async_redis_adapter-1.2.0.dist-info/METADATA
casbin_async_redis_adapter-1.2.0.dist-info/WHEEL
casbin_async_redis_adapter-1.2.0.dist-info/top_level.txt
casbin_async_redis_adapter-1.2.0.dist-info/RECORD
