Metadata-Version: 2.1
Name: casbin_async_redis_adapter
Version: 1.2.0
Summary: Async Redis Adapter for PyCasbin
Home-page: https://github.com/pycasbin/async-redis-adapter
Author: BustDot
Author-email: Bust.dev@outlook.com
License: Apache 2.0
Keywords: casbin,Redis,casbin-adapter,async,rbac,access control,abac,acl,permission
Classifier: Programming Language :: Python :: 3.9
Classifier: Programming Language :: Python :: 3.10
Classifier: Programming Language :: Python :: 3.11
Classifier: Programming Language :: Python :: 3.12
Classifier: License :: OSI Approved :: Apache Software License
Classifier: Operating System :: OS Independent
Requires-Python: >=3.8
License-File: LICENSE
Requires-Dist: casbin >=1.34.0
Requires-Dist: redis >=5.0.0
